py_micro_services/core.py
py_micro_services/discovery_server.py
py_micro_services/gateway.py
py_micro_services-0.2.1.dist-info/METADATA
py_micro_services-0.2.1.dist-info/WHEEL
py_micro_services-0.2.1.dist-info/top_level.txt
py_micro_services-0.2.1.dist-info/RECORD
